nr/__init__.py
nr/collections/__init__.py
nr/collections/chaindict.py
nr/collections/orderedset.py
nr.collections-1.0.0.dist-info/LICENSE.txt
nr.collections-1.0.0.dist-info/METADATA
nr.collections-1.0.0.dist-info/WHEEL
nr.collections-1.0.0.dist-info/top_level.txt
nr.collections-1.0.0.dist-info/zip-safe
nr.collections-1.0.0.dist-info/RECORD
