Metadata-Version: 2.1
Name: nr.collections
Version: 1.0.0
Summary: Useful container datatypes for Python 2 and 3.
Home-page: https://git.niklasrosenstein.com/NiklasRosenstein/nr
Author: Niklas Rosenstein
Author-email: rosensteinniklas@gmail.com
License: MIT
Platform: UNKNOWN
Requires-Python: >=3.6.0,<4.0.0
License-File: LICENSE.txt
